examplepkgjanewilliams/Class1.py
examplepkgjanewilliams/__init__.py
examplepkgjanewilliams-0.1.dist-info/LICENSE
examplepkgjanewilliams-0.1.dist-info/METADATA
examplepkgjanewilliams-0.1.dist-info/WHEEL
examplepkgjanewilliams-0.1.dist-info/top_level.txt
examplepkgjanewilliams-0.1.dist-info/RECORD
